pathutility/__init__.py
pathutility/_routing.py
pathutility/_version.py
pathutility/pathutils.py
pathutility/utils/__init__.py
pathutility/utils/errors.py
pathutility-1.0.0.dist-info/METADATA
pathutility-1.0.0.dist-info/WHEEL
pathutility-1.0.0.dist-info/top_level.txt
pathutility-1.0.0.dist-info/RECORD
