Metadata-Version: 2.1
Name: pathutility
Version: 1.0.0
Summary: pathutility is a Python library for working with file paths.
Author: Marc anglisano
Author-email: marcanglisano@gmail.com
Project-URL: Documentation, https://anglisanosa.github.io/pathutility/
Project-URL: Bug Reports, https://github.com/anglisanosa/pathutility/issues
Project-URL: Source, https://github.com/anglisanosa/pathutility
Classifier: Programming Language :: Python :: 3
Classifier: Operating System :: OS Independent
Requires-Python: >=3.8
Requires-Dist: chardet
